vijay_tool.py
vijay_dir/__init__.py
vijay_dir/__main__.py
vijay_dir/vijay_logic.py
vijay-0.0.1.dist-info/LICENSE
vijay-0.0.1.dist-info/METADATA
vijay-0.0.1.dist-info/WHEEL
vijay-0.0.1.dist-info/entry_points.txt
vijay-0.0.1.dist-info/top_level.txt
vijay-0.0.1.dist-info/RECORD
