Metadata-Version: 2.1
Name: vijay
Version: 0.0.1
Summary: vijay
Home-page: UNKNOWN
Author: Vijay Thorat
Author-email: vijaythorat0804@gmail.com
License: MIT License
Platform: UNKNOWN
Classifier: Programming Language :: Python :: 3.8
Classifier: Operating System :: OS Independent
Requires-Python: >=3.7
Requires-Dist: Click (==7.0)
Requires-Dist: requests (==2.28.1)
Requires-Dist: setuptools (==45.2.0)
